huacaicai/__init__.py
huacaicai/common.py
huacaicai/huacaicai.py
huacaicai-0.0.1.dist-info/LICENSE
huacaicai-0.0.1.dist-info/METADATA
huacaicai-0.0.1.dist-info/WHEEL
huacaicai-0.0.1.dist-info/entry_points.txt
huacaicai-0.0.1.dist-info/top_level.txt
huacaicai-0.0.1.dist-info/RECORD
